funfolding/__init__.py
funfolding/binning/__init__.py
funfolding/binning/_binning.py
funfolding/binning/classic_binning.py
funfolding/binning/tree_sklearn_based.py
funfolding/model/__init__.py
funfolding/model/_model.py
funfolding/pipeline/__init__.py
funfolding/pipeline/_feature_selection.py
funfolding/pipeline/_pipeline.py
funfolding/solution/__init__.py
funfolding/solution/_dsea.py
funfolding/solution/_solution.py
funfolding/solution/error_calculation.py
funfolding/solution/likelihood.py
funfolding/visualization/__init__.py
funfolding/visualization/visualize_classic_binning.py
funfolding/visualization/visualize_llh.py
funfolding/visualization/visualize_model.py
funfolding/visualization/visualize_tree_binning.py
funfolding-0.3.0.dist-info/LICENSE
funfolding-0.3.0.dist-info/METADATA
funfolding-0.3.0.dist-info/WHEEL
funfolding-0.3.0.dist-info/top_level.txt
funfolding-0.3.0.dist-info/RECORD
